zgame/__init__.py
zgame-1.0.0.dist-info/licenses/LICENSE
zgame-1.0.0.dist-info/METADATA
zgame-1.0.0.dist-info/WHEEL
zgame-1.0.0.dist-info/top_level.txt
zgame-1.0.0.dist-info/RECORD
