Metadata-Version: 2.4
Name: zgame
Version: 1.0.0
Summary: A beginner-friendly 2D game engine for Python
Author: Zhvan
License: MIT
Project-URL: Homepage, https://github.com/Zhvan14/zgame
Requires-Python: >=3.8
License-File: LICENSE
Requires-Dist: pygame>=2.0
Dynamic: license-file
